[
{
    "DisplayName": "taponme",
    "Name": "taponme",
    "Skin": "taponme",
    "Model": "humanoid",
    "Color": "&1",
    "ClickedOnText": "1. No Being Rude to kids 2. no greifing 3. no messing",
    "DeathMessage": null,
    "Owner": "PetsGamer+",
    "AI": null,
    "Kill": false,
    "Hunt": false,
    "CurInstruction": 0,
    "CurJump": 0,
    "CurSpeed": 3,
    "X": 1902,
    "Y": 2102,
    "Z": 2512,
    "RotX": 128,
    "RotY": 0,
    "BodyX": 0,
    "BodyZ": 0,
    "ScaleX": 0,
    "ScaleY": 0,
    "ScaleZ": 0
},
{
    "DisplayName": "Guard1",
    "Name": "Guard1",
    "Skin": "Guard1",
    "Model": "humanoid",
    "Color": "&1",
    "ClickedOnText": null,
    "DeathMessage": null,
    "Owner": "PetsGamer+",
    "AI": null,
    "Kill": false,
    "Hunt": false,
    "CurInstruction": 0,
    "CurJump": 0,
    "CurSpeed": 3,
    "X": 1930,
    "Y": 2099,
    "Z": 2587,
    "RotX": 2,
    "RotY": 0,
    "BodyX": 0,
    "BodyZ": 0,
    "ScaleX": 0,
    "ScaleY": 0,
    "ScaleZ": 0
},
{
    "DisplayName": "Guard2",
    "Name": "Guard2",
    "Skin": "Guard2",
    "Model": "humanoid",
    "Color": "&1",
    "ClickedOnText": null,
    "DeathMessage": null,
    "Owner": "PetsGamer+",
    "AI": null,
    "Kill": false,
    "Hunt": false,
    "CurInstruction": 0,
    "CurJump": 0,
    "CurSpeed": 3,
    "X": 2107,
    "Y": 2099,
    "Z": 2587,
    "RotX": 0,
    "RotY": 0,
    "BodyX": 0,
    "BodyZ": 0,
    "ScaleX": 0,
    "ScaleY": 0,
    "ScaleZ": 0
}]
