[
{
    "DisplayName": "whwt1borpluu419",
    "Name": "whwt1borpluu419",
    "Skin": "whwt1borpluu419",
    "Model": "humanoid",
    "Color": "&1",
    "ClickedOnText": "uhh were a beach?",
    "DeathMessage": null,
    "Owner": "Alexcrish17+",
    "AI": null,
    "Kill": false,
    "Hunt": false,
    "CurInstruction": 0,
    "CurJump": 0,
    "CurSpeed": 3,
    "X": 1560,
    "Y": 2067,
    "Z": 428,
    "RotX": 59,
    "RotY": 0,
    "BodyX": 0,
    "BodyZ": 0,
    "ScaleX": 0,
    "ScaleY": 0,
    "ScaleZ": 0
},
{
    "DisplayName": "Alexcrish17",
    "Name": "Alexcrish17",
    "Skin": "Alexcrish17",
    "Model": "humanoid",
    "Color": "&1",
    "ClickedOnText": "No This is a Sea",
    "DeathMessage": null,
    "Owner": "Alexcrish17+",
    "AI": null,
    "Kill": false,
    "Hunt": false,
    "CurInstruction": 0,
    "CurJump": 0,
    "CurSpeed": 3,
    "X": 1635,
    "Y": 2067,
    "Z": 493,
    "RotX": 219,
    "RotY": 0,
    "BodyX": 0,
    "BodyZ": 0,
    "ScaleX": 0,
    "ScaleY": 0,
    "ScaleZ": 0
},
{
    "DisplayName": "prolikeagamer",
    "Name": "prolikeagamer",
    "Skin": "prolikeagamer",
    "Model": "humanoid",
    "Color": "&1",
    "ClickedOnText": "its a aral sea",
    "DeathMessage": null,
    "Owner": "Alexcrish17+",
    "AI": null,
    "Kill": false,
    "Hunt": false,
    "CurInstruction": 0,
    "CurJump": 0,
    "CurSpeed": 3,
    "X": 1661,
    "Y": 2067,
    "Z": 399,
    "RotX": 173,
    "RotY": 0,
    "BodyX": 0,
    "BodyZ": 0,
    "ScaleX": 0,
    "ScaleY": 0,
    "ScaleZ": 0
},
{
    "DisplayName": "Dinosaur",
    "Name": "Dinosaur",
    "Skin": "Dinosaur",
    "Model": "humanoid",
    "Color": "&1",
    "ClickedOnText": "I Know",
    "DeathMessage": null,
    "Owner": "Alexcrish17+",
    "AI": null,
    "Kill": false,
    "Hunt": false,
    "CurInstruction": 0,
    "CurJump": 0,
    "CurSpeed": 3,
    "X": 1600,
    "Y": 2083,
    "Z": 392,
    "RotX": 123,
    "RotY": 0,
    "BodyX": 0,
    "BodyZ": 0,
    "ScaleX": 0,
    "ScaleY": 0,
    "ScaleZ": 0
},
{
    "DisplayName": "Villager",
    "Name": "Villager",
    "Skin": "Villager",
    "Model": "humanoid",
    "Color": "&1",
    "ClickedOnText": "oh i think idk",
    "DeathMessage": null,
    "Owner": "Alexcrish17+",
    "AI": null,
    "Kill": false,
    "Hunt": false,
    "CurInstruction": 0,
    "CurJump": 0,
    "CurSpeed": 3,
    "X": 1542,
    "Y": 2099,
    "Z": 3123,
    "RotX": 255,
    "RotY": 0,
    "BodyX": 0,
    "BodyZ": 0,
    "ScaleX": 0,
    "ScaleY": 0,
    "ScaleZ": 0
},
{
    "DisplayName": "man",
    "Name": "man",
    "Skin": "man",
    "Model": "humanoid",
    "Color": "&1",
    "ClickedOnText": "uhh guys?",
    "DeathMessage": null,
    "Owner": "Alexcrish17+",
    "AI": null,
    "Kill": false,
    "Hunt": false,
    "CurInstruction": 0,
    "CurJump": 0,
    "CurSpeed": 3,
    "X": 1176,
    "Y": 2099,
    "Z": 204,
    "RotX": 84,
    "RotY": 0,
    "BodyX": 0,
    "BodyZ": 0,
    "ScaleX": 0,
    "ScaleY": 0,
    "ScaleZ": 0
},
{
    "DisplayName": "Villager1",
    "Name": "Villager1",
    "Skin": "Villager1",
    "Model": "humanoid",
    "Color": "&1",
    "ClickedOnText": "Bruh?",
    "DeathMessage": null,
    "Owner": "Alexcrish17+",
    "AI": null,
    "Kill": false,
    "Hunt": false,
    "CurInstruction": 0,
    "CurJump": 0,
    "CurSpeed": 3,
    "X": 1515,
    "Y": 2099,
    "Z": 3159,
    "RotX": 10,
    "RotY": 0,
    "BodyX": 0,
    "BodyZ": 0,
    "ScaleX": 0,
    "ScaleY": 0,
    "ScaleZ": 0
}]
